Single cycle processor/src/fpu.v
module fpu(
    a,
    b,
    FPUControl,
    Result,
    FPUFlags
);
    //32 bits: 1 bit sign, 8 bit expo, 23 bit mantisa
    //16 bits. 1 bit sign, 5 bit expo, 10 bit mantisa
    input [31:0] a, b;
    input [1:0] FPUControl;  //00 suma 16 bits, 01 suma 32 bits, 10 producto 16 bits, 11 producto 32 bits
    output reg [31:0] Result;
    output wire [3:0] FPUFlags;

    wire neg, zero, carry, overflow;

    reg signA;
    reg signB;
    reg [31:0] expoA;
    reg [31:0] expoB;
    reg [31:0] mantA;
    reg [31:0] mantB;
    
    reg sumaResta;
    reg signR;
    reg [31:0] expoR;
    reg [31:0] mantR;
    reg [31:0] mantAshift;
    reg [31:0] mantBshift;
    reg [47:0] productoPosible;
    reg [31:0] aux;
    reg [47:0] aux2;
    reg [1:0] control;
    
    always @(*) begin
        control = FPUControl;
        //Separo los componentes
        signA = FPUControl[0] ? a[31] : a[15];
        signB = FPUControl[0] ? b[31] : b[15];
        
        //Agrego 24 o 27 zeros delante del exponente
        expoA = FPUControl[0] ? {24'b0, a[30:23]} : {27'b0, a[14:10]};
        expoB = FPUControl[0] ? {24'b0, b[30:23]} : {27'b0, b[14:10]};

        //Agrego un 1 delante de la mantisa
        mantA = FPUControl[0] ? {9'b1, a[22:0]} : {22'b1, a[9:0]};
        mantB = FPUControl[0] ? {9'b1, b[22:0]} : {22'b1, b[9:0]};
        
        if (~FPUControl[1]) begin
            //Suma
            if ((a == 0 && b != 0) || a != 0 && b == 0) begin
                signR = (a == 0) ? signB : signA;
                expoR = (a == 0) ? expoB : expoA;
                mantR = (a == 0) ? mantB : mantA;
            end
            else if ((a == 0 && b == 0) || (signA != signB && expoA == expoB && mantA == mantB)) begin
                signR = 0;
                expoR = 0;
                mantR = 0;
            end
            else begin
                if (expoA > expoB) begin
                    expoR = expoA;
                    mantB = mantB >> (expoA - expoB);
                end
                else begin
                    expoR = expoB;
                    mantA = mantA >> (expoB - expoA);
                end

                //sumaResta, //0 sumar, 1 restar
                sumaResta = ~(signA == signB);

                if (sumaResta) begin
                    if (mantA > mantB) begin
                        mantR = mantA - mantB;
                        signR = signA;
                    end
                    else begin
                        mantR = mantB - mantA;
                        signR = signB;
                    end
                end
                else begin
                    mantR = mantA + mantB;
                    signR = signA;
                end
                    
                if (sumaResta) begin
                    //RESTA: Busco el primer 1
                    //mantR != 0, porque valido al inicio
                    aux = 0;
                    //En aux guardo en qué bit está el primer 1 a la izquierda
                    //naturalmente es menor a 23 o 10, ya que restamos el mayor - menor
                    aux2 = mantR;
                    while(~aux2[31]) begin
                        aux2 = aux2 << 1;
                        aux = aux + 1;
                    end
                    aux = 31 - aux;
                    //Este bit debe regresar a la posicion 23 o 10 para normalizar la mantisa
                    //Cada desplazamiento debe restar 1 al exponente
                    mantR = mantR << ((FPUControl[0] ? 23 : 10) - aux);
                    expoR = expoR - ((FPUControl[0] ? 23 : 10) - aux);
                end
                else begin
                    //SUMA:
                    if ((control[0] && mantR[24] == 1'b1) || (~control[0] && mantR[11] == 1'b1)) begin
                        //Overflow
                        mantR = mantR >> 1'b1;
                        expoR = expoR + 1'b1;
                    end
                end
                
                //Quitar el 1 delante de la mantisa
                mantR = FPUControl[0] ? mantR[22:0] : mantR[9:0];
            end
        end
        else begin
            if (a == 0 || b == 0) begin
                signR = 0;
                expoR = 0;
                mantR = 0;
            end
            else begin
                expoR = expoA + expoB - (FPUControl[0] ? 8'b01111111 : 5'b01111);
                //Desplazo a la derecha las mantisas eliminando todos los ending zeros.
                mantAshift = 0; //Guarda cuantos bits a la derecha se mueve.
                mantBshift = 0;
                while(~mantA[0]) begin
                    mantA = mantA >> 1;
                    mantAshift = mantAshift + 1;
                end
                while(~mantB[0]) begin
                    mantB = mantB >> 1;
                    mantBshift = mantBshift + 1;
                end
                
                //Multiplico las mantisas, máximo número puede ser de 48 bits o 22 bits
                if (FPUControl[0])
                    productoPosible = {16'b0, mantA} * {16'b0, mantB};
                else
                    productoPosible = mantA * mantB;
                
                aux = 0;
                //productoPosible tiene 1 o 2 bits de parte entera
                //En aux guardo en qué bit está el primer 1 a la izquierda
                aux2 = productoPosible;
                while(~aux2[47]) begin
                    aux2 = aux2 << 1;
                    aux = aux + 1;
                end
                aux = 47 - aux;
                //Si aux+1 - # bits decimales en ambas mantisas > 1 (=2), sumo uno al exponente
                if ( ( (aux + 1) - ((FPUControl[0] ? 23 : 10) - mantAshift + (FPUControl[0] ? 23 : 10) - mantBshift) ) > 1) begin
                    expoR = expoR + 1;
                end

                //Caso 1: aux = 23, entonces ya tiene forma de mantisa (leading 1 y 23 bits después, 0 a 22)
                //Caso 1: aux = 10, entonces ya tiene forma de mantisa (leading 1 y 10 bits después, 0 a 9)
                //Caso 2: aux > 23, shift right, se puede perder información en los bits menos significativos
                //Caso 2: aux > 10, shift right, se puede perder información en los bits menos significativos
                if (aux > (FPUControl[0] ? 23 : 10))
                    productoPosible = productoPosible >> (aux - (FPUControl[0] ? 23 : 10));
                //Caso 3: aux < 23, shift left para darle forma
                //Caso 3: aux < 10, shift left para darle forma
                if (aux < (FPUControl[0] ? 23 : 10))
                    productoPosible = productoPosible << ((FPUControl[0] ? 23 : 10) - aux);

                //Quitar el 1 delante de la mantisa
                mantR = FPUControl[0] ? productoPosible[22:0] : productoPosible[9:0];

                //Signo
                signR = signA ^ signB;
            end
        end
        Result = FPUControl[0] ? {signR, expoR[7:0], mantR[22:0]} : {signR, expoR[4:0], mantR[9:0]};
    end

    assign carry = 1'b0;
    assign overflow = 1'b0;
    assign neg = FPUControl[0] ? Result[31] : Result[15];
    assign zero = Result == 32'b0;
    
    assign FPUFlags = {neg, zero, carry, overflow};

endmodule

FP Unit/fpu_tb.v
`timescale 1ns/1ns

/*
//testvector.tv
//FPUControl_A_B_Resultexpected
//01
//0:    1.0 + 1.0=2.0
//1:    23.0 + 15.5 = 38.5
//2:    7.875 + 0.1875 = 8.0625
//3:    0.125 + 100032.125 = 100032.25
//4:    1.5 + 1.5 = 3.0
//5:    1.5 + 0 = 1.5
//6:    0 + 1.5 = 1.5
//7:    -1.5 + 1.5 = 0
//8:    1.5 - 1.5 = 0
//9:    6.875 - 15.5 = -8.625
//10:   15.5 - 6.875 = 8.625

//00
//11:   1.625 + 0.5 = 2.125 
//12:   0.875 + 10.5 = 11.375
//13:   64.4375+18.015625 = 82.453125

//11:
//14:   1.0 * 1.0 = 1.0
//15:   1.5 * 1.5 = 2.25
//16:   312.4375 * 124.8125 = 38996.10546875
//17:   0.03125 * 7.8125 = 0.244140625 
//18:   -1.0*-1.0 = 1.0
//19:   -1.0*1.0 = -1.0
//20:   1.0*-1.0 = -1.0
//21:   1.0*0.0=0.0
//22:   0.0*0.0=0.0

//10:
//23:   1.625 * 0.5 = 0.8125
//24:   0.03125 * 7.8125 = 0.244140625 
//25:   0.0*0.0=0.0
*/

module fpu_tb();
    reg [31:0] a,b;
    reg [1:0] FPUControl;
    wire [31:0] Result;
    wire [3:0] FPUFlags;

    reg clk, reset;
    reg [101:0] testvector[1000:0];
    
    reg [31:0] Result_expected; // to compare y output
    reg [3:0] FPUFlags_expected; // to compare y output
    reg [31:0] vectornum; // check testvector number
    reg [31:0] errors; // error counter
    
    fpu dut(.a(a), .b(b), .FPUControl(FPUControl), .Result(Result), .FPUFlags(FPUFlags));
    
    always// always execute
        begin
            clk=1; #5; clk=0; #5;   //period? Tc= 10
        end
    
    initial // one exec 
        begin
            $readmemh("testvector.tv",testvector); //read in hexa
            errors=0;
            vectornum=0;
            reset=1; #17;reset=0;
        end
    
    always @(posedge clk)
        begin
            FPUFlags_expected = testvector[vectornum][3:0];
            Result_expected = testvector[vectornum][35:4];
            a = testvector[vectornum][67:36];
            b = testvector[vectornum][99:68];
            FPUControl = testvector[vectornum][101:100];
        end
    
    always @(negedge clk)
        begin
            if (~reset)
                begin 
                    if ((Result !== Result_expected) || (FPUFlags !== FPUFlags_expected))  // ===, == 
                        begin
                          $display("testvector: %h",testvector[vectornum]);
                          $display("Vectornum: %d",vectornum);
                          $display("Error input a: %h",{a});
                          $display("Error input b: %h",{b});
                          $display("Error input FPUControl: %h",{FPUControl});
                          $display("output Result:%h, Result_expected:%h",Result,Result_expected);
                          $display("output FPUFlags:%h, FPUFlags_expected:%h",FPUFlags,FPUFlags_expected);
                          errors=errors+1; 
                        end
                    vectornum=vectornum+1;
                
                    if (testvector[vectornum][0] === 1'bx)
                        begin
                            $display("total errors: %d",errors);
                            $finish;
                        end  
                end
        end
    initial begin
      $dumpfile("fpu.vcd");
      $dumpvars;
    end
endmodule

FP Unit/fpu.vcd
$date
	Mon Jul 26 22:11:55 2021
$end
$version
	Icarus Verilog
$end
$timescale
	1ns
$end
$scope module fpu_tb $end
$var wire 32 ! Result [31:0] $end
$var wire 4 " FPUFlags [3:0] $end
$var reg 2 # FPUControl [1:0] $end
$var reg 4 $ FPUFlags_expected [3:0] $end
$var reg 32 % Result_expected [31:0] $end
$var reg 32 & a [31:0] $end
$var reg 32 ' b [31:0] $end
$var reg 1 ( clk $end
$var reg 32 ) errors [31:0] $end
$var reg 1 * reset $end
$var reg 32 + vectornum [31:0] $end
$scope module dut $end
$var wire 2 , FPUControl [1:0] $end
$var wire 32 - a [31:0] $end
$var wire 32 . b [31:0] $end
$var wire 1 / carry $end
$var wire 1 0 overflow $end
$var wire 1 1 zero $end
$var wire 1 2 neg $end
$var wire 4 3 FPUFlags [3:0] $end
$var reg 32 4 Result [31:0] $end
$var reg 32 5 aux [31:0] $end
$var reg 48 6 aux2 [47:0] $end
$var reg 2 7 control [1:0] $end
$var reg 32 8 expoA [31:0] $end
$var reg 32 9 expoB [31:0] $end
$var reg 32 : expoR [31:0] $end
$var reg 32 ; mantA [31:0] $end
$var reg 32 < mantAshift [31:0] $end
$var reg 32 = mantB [31:0] $end
$var reg 32 > mantBshift [31:0] $end
$var reg 32 ? mantR [31:0] $end
$var reg 48 @ productoPosible [47:0] $end
$var reg 1 A signA $end
$var reg 1 B signB $end
$var reg 1 C signR $end
$var reg 1 D sumaResta $end
$upscope $end
$upscope $end
$enddefinitions $end
#0
$dumpvars
xD
xC
xB
xA
bx @
bx ?
bx >
bx =
bx <
bx ;
bx :
bx 9
bx 8
bx 7
bx 6
bx 5
bx 4
bx00 3
x2
x1
00
0/
bx .
bx -
bx ,
b0 +
1*
b0 )
1(
bx '
bx &
bx %
bx $
bx #
bx00 "
bx !
$end
#5
0(
#10
02
b0 "
b0 3
01
b1000000000000000000000000000000 !
b1000000000000000000000000000000 4
0C
b0 ?
0D
b10000000 :
b100000000000000000000000 =
b100000000000000000000000 ;
b1111111 9
b1111111 8
0B
0A
b1 7
b1 #
b1 ,
b111111100000000000000000000000 '
b111111100000000000000000000000 .
b111111100000000000000000000000 &
b111111100000000000000000000000 -
b1000000000000000000000000000000 %
b0 $
1(
#15
0(
#17
0*
#20
1(
#25
b1 +
0(
#30
b1000010000110100000000000000000 !
b1000010000110100000000000000000 4
b110100000000000000000 ?
b10000100 :
b101110000000000000000000 =
b11111000000000000000000 ;
b10000011 9
b10000010 8
b1000001101110000000000000000000 '
b1000001101110000000000000000000 .
b1000001011110000000000000000000 &
b1000001011110000000000000000000 -
b1000010000110100000000000000000 %
1(
#35
b10 +
0(
#40
b1000001000000010000000000000000 !
b1000001000000010000000000000000 4
b10000000000000000 ?
b10000010 :
b111111000000000000000000 =
b1100000000000000000 ;
b10000001 9
b1111100 8
b1000000111111000000000000000000 '
b1000000111111000000000000000000 .
b111110010000000000000000000000 &
b111110010000000000000000000000 -
b1000001000000010000000000000000 %
1(
#45
b11 +
0(
#50
b1000111110000110110000000100000 !
b1000111110000110110000000100000 4
b10000110110000000100000 ?
b10001111 :
b10000 =
b110000110110000000010000 ;
b1111100 9
b10001111 8
b111110000000000000000000000000 '
b111110000000000000000000000000 .
b1000111110000110110000000010000 &
b1000111110000110110000000010000 -
b1000111110000110110000000100000 %
1(
#55
b100 +
0(
#60
b1000000010000000000000000000000 !
b1000000010000000000000000000000 4
b10000000000000000000000 ?
b10000000 :
b110000000000000000000000 =
b110000000000000000000000 ;
b1111111 9
b1111111 8
b111111110000000000000000000000 '
b111111110000000000000000000000 .
b111111110000000000000000000000 &
b111111110000000000000000000000 -
b1000000010000000000000000000000 %
1(
#65
b101 +
0(
#70
b111111110000000000000000000000 !
b111111110000000000000000000000 4
b110000000000000000000000 ?
b1111111 :
b100000000000000000000000 ;
b0 8
b0 &
b0 -
b111111110000000000000000000000 %
1(
#75
b110 +
0(
#80
b100000000000000000000000 =
b110000000000000000000000 ;
b0 9
b1111111 8
b0 '
b0 .
b111111110000000000000000000000 &
b111111110000000000000000000000 -
1(
#85
b111 +
0(
#90
b100 "
b100 3
11
b0 !
b0 4
b0 ?
b0 :
b110000000000000000000000 =
b1111111 9
1B
b10111111110000000000000000000000 '
b10111111110000000000000000000000 .
b0 %
b100 $
1(
#95
b1000 +
0(
#100
0B
1A
b111111110000000000000000000000 '
b111111110000000000000000000000 .
b10111111110000000000000000000000 &
b10111111110000000000000000000000 -
1(
#105
b1001 +
0(
#110
12
b1000 "
b1000 3
01
b11000001000010100000000000000000 !
b11000001000010100000000000000000 4
b10001010000000000000000000000000 6
b10111 5
1C
b10100000000000000000 ?
1D
b10000010 :
b11011100000000000000000 =
b111110000000000000000000 ;
b10000001 9
b10000010 8
b1000000110111000000000000000000 '
b1000000110111000000000000000000 .
b11000001011110000000000000000000 &
b11000001011110000000000000000000 -
b11000001000010100000000000000000 %
b1000 $
1(
#115
b1010 +
0(
#120
b0 "
b0 3
02
b1000001000010100000000000000000 !
b1000001000010100000000000000000 4
b10001010000000000000000000000000 6
b10111 5
0C
b10100000000000000000 ?
b111110000000000000000000 =
b11011100000000000000000 ;
b10000010 9
b10000001 8
b1000001011110000000000000000000 '
b1000001011110000000000000000000 .
b11000000110111000000000000000000 &
b11000000110111000000000000000000 -
b1000001000010100000000000000000 %
b0 $
1(
#125
b1011 +
0(
#130
b100000001000000 !
b100000001000000 4
b1000000 ?
0D
b10000 :
b11010000000 =
b1000000000 ;
b1111 9
b1110 8
0A
b0 7
b0 #
b0 ,
b11111010000000 '
b11111010000000 .
b11100000000000 &
b11100000000000 -
b100000001000000 %
1(
#135
b1100 +
0(
#140
b100100110110000 !
b100100110110000 4
b110110000 ?
b10010 :
b1110000 =
b10101000000 ;
b1110 9
b10010 8
b11101100000000 '
b11101100000000 .
b100100101000000 &
b100100101000000 -
b100100110110000 %
1(
#145
b1101 +
0(
#150
b101010100100111 !
b101010100100111 4
b100100111 ?
b10101 :
b10000000111 =
b100100000 ;
b10101 9
b10011 8
b101010000000111 '
b101010000000111 .
b100110010000001 &
b100110010000001 -
b101010100100111 %
1(
#155
b1110 +
0(
#160
b111111100000000000000000000000 !
b111111100000000000000000000000 4
b0 ?
b100000000000000000000000000000000000000000000000 6
b0 5
b100000000000000000000000 @
b10111 >
b10111 <
b1111111 :
b1 =
b1 ;
b1111111 9
b1111111 8
b11 7
b11 #
b11 ,
b111111100000000000000000000000 '
b111111100000000000000000000000 .
b111111100000000000000000000000 &
b111111100000000000000000000000 -
b111111100000000000000000000000 %
1(
#165
b1111 +
0(
#170
b1000000000100000000000000000000 !
b1000000000100000000000000000000 4
b100000000000000000000 ?
b10000000 :
b11 5
b100100000000000000000000000000000000000000000000 6
b100100000000000000000000 @
b10110 >
b10110 <
b11 =
b11 ;
b111111110000000000000000000000 '
b111111110000000000000000000000 .
b111111110000000000000000000000 &
b111111110000000000000000000000 -
b1000000000100000000000000000000 %
1(
#175
b10000 +
0(
#180
b1000111000110000101010000011011 !
b1000111000110000101010000011011 4
b110000101010000011011 ?
b100110000101010000011011000000000000000000000000 6
b10111 5
b100110000101010000011011 @
b1011 >
b1101 <
b10001110 :
b1001110000111 =
b11111001101 ;
b10000111 9
b10000101 8
b1000011100111000011100000000000 '
b1000011100111000011100000000000 .
b1000010111110011010000000000000 &
b1000010111110011010000000000000 -
b1000111000110000101010000011011 %
1(
#185
b10001 +
0(
#190
b111110011110100000000000000000 !
b111110011110100000000000000000 4
b11110100000000000000000 ?
b111110100000000000000000000000000000000000000000 6
b110 5
b111110100000000000000000 @
b10111 >
b10001 <
b1111100 :
b1 =
b1111101 ;
b1111010 9
b10000001 8
b111101000000000000000000000000 '
b111101000000000000000000000000 .
b1000000111110100000000000000000 &
b1000000111110100000000000000000 -
b111110011110100000000000000000 %
1(
#195
b10010 +
0(
#200
b111111100000000000000000000000 !
b111111100000000000000000000000 4
b0 ?
b100000000000000000000000000000000000000000000000 6
b0 5
b100000000000000000000000 @
b10111 >
b10111 <
b1111111 :
b1 =
b1 ;
b1111111 9
b1111111 8
1B
1A
b10111111100000000000000000000000 '
b10111111100000000000000000000000 .
b10111111100000000000000000000000 &
b10111111100000000000000000000000 -
b111111100000000000000000000000 %
1(
#205
b10011 +
0(
#210
b1000 "
b1000 3
12
b10111111100000000000000000000000 !
b10111111100000000000000000000000 4
1C
b0 5
b100000000000000000000000000000000000000000000000 6
b100000000000000000000000 @
b10111 >
b10111 <
b1 =
b1 ;
0A
b111111100000000000000000000000 &
b111111100000000000000000000000 -
b10111111100000000000000000000000 %
b1000 $
1(
#215
b10100 +
0(
#220
b0 5
b100000000000000000000000000000000000000000000000 6
b100000000000000000000000 @
b10111 >
b10111 <
b1 =
b1 ;
0B
1A
b111111100000000000000000000000 '
b111111100000000000000000000000 .
b10111111100000000000000000000000 &
b10111111100000000000000000000000 -
1(
#225
b10101 +
0(
#230
02
b100 "
b100 3
11
b0 !
b0 4
b0 :
0C
b100000000000000000000000 =
b100000000000000000000000 ;
b0 8
0A
b0 &
b0 -
b0 %
b100 $
1(
#235
b10110 +
0(
#240
b0 9
b0 '
b0 .
1(
#245
b10111 +
0(
#250
b0 "
b0 3
01
b11101010000000 !
b11101010000000 4
b1010000000 ?
b11 5
b110100000000000000000000000000000000000000000000 6
b11010000000 @
b111 >
b1010 <
b1110 :
b1101 =
b1 ;
b1111 9
b1110 8
b10 7
b10 #
b10 ,
b11111010000000 '
b11111010000000 .
b11100000000000 &
b11100000000000 -
b11101010000000 %
b0 $
1(
#255
b11000 +
0(
#260
b11001111010000 !
b11001111010000 4
b1111010000 ?
b111110100000000000000000000000000000000000000000 6
b110 5
b11111010000 @
b1010 >
b100 <
b1100 :
b1 =
b1111101 ;
b1010 9
b10001 8
b10100000000000 '
b10100000000000 .
b100011111010000 &
b100011111010000 -
b11001111010000 %
1(
#265
b11001 +
0(
#270
b100 "
b100 3
11
b0 !
b0 4
b0 ?
b0 :
b10000000000 =
b10000000000 ;
b0 9
b0 8
b0 '
b0 .
b0 &
b0 -
b0 %
b100 $
1(
#275
b11010 +
0(
