FP Unit/fpu.v
module fpu(
    a,
    b,
    FPUControl,
    Result
);
    //32 bits: 1 bit sign, 8 bit expo, 23 bit mantisa
    //16 bits. 1 bit sign, 5 bit expo, 10 bit mantisa
    input [31:0] a, b;
    input [1:0] FPUControl;  //00 suma 16 bits, 01 suma 32 bits, 10 producto 16 bits, 11 producto 32 bits
    output reg [31:0] Result;

    reg signA;
    reg signB;
    reg [31:0] expoA;
    reg [31:0] expoB;
    reg [31:0] mantA;
    reg [31:0] mantB;
    
    reg signR = 1'b0;
    reg [31:0] expoR;
    reg [31:0] mantR;

    reg [1:0] control;

    always @(*) begin
        control = FPUControl;
        //Separo los componentes
        signA = FPUControl[0] ? a[31] : a[15];
        signB = FPUControl[0] ? b[31] : b[15];
        
        //Agrego 24 o 27 zeros delante del exponente
        expoA = FPUControl[0] ? {24'b0, a[30:23]} : {27'b0, a[14:10]};
        expoB = FPUControl[0] ? {24'b0, b[30:23]} : {27'b0, b[14:10]};

        //Agrego un 1 delante de la mantisa
        mantA = FPUControl[0] ? {9'b1, a[22:0]} : {22'b1, a[9:0]};
        mantB = FPUControl[0] ? {9'b1, b[22:0]} : {22'b1, b[9:0]};
        
        if (FPUControl[1] == 1'b0) begin
            if (expoA > expoB) begin
                expoR = expoA;
                mantB = mantB >> (expoA - expoB);
            end
            else begin
                expoR = expoB;
                mantA = mantA >> (expoB - expoA);
            end
            mantR = mantA + mantB;

            if (control[0] ? (mantR[24] == 1'b1) : (mantR[11] == 1'b1)) begin
                //Overflow
                mantR = mantR >> 1'b1;
                expoR = expoR + 1'b1;
            end

            //Quitar el 1 delante de la mantisa
            mantR = FPUControl[0] ? mantR[22:0] : mantR[9:0];
        end
        
        Result = FPUControl[0] ? {signR, expoR[7:0], mantR[22:0]} : {signR, expoR[4:0], mantR[9:0]};
    end
    
endmodule

FP Unit/fpu_tb.v
`timescale 1ns/1ns

/*
//testvector.tv
//FPUControl_A_B_Resultexpected
//1.0+1.0=2.0
1_3f800000_3f800000_40000000
X_XXXXXXXX_XXXXXXXX_XXXXXXXX
*/

module fpu_tb();
    reg [31:0] a,b;
    reg [1:0] FPUControl;
    wire [31:0] Result;

    reg clk, reset;
    reg [101:0] testvector[1000:0];
    
    reg [31:0] Result_expected; // to compare y output
    reg [31:0] vectornum; // check testvector number
    reg [31:0] errors; // error counter
    
    fpu dut(.a(a), .b(b), .FPUControl(FPUControl), .Result(Result));
    
    always// always execute
        begin
            clk=1; #5; clk=0; #5;   //period? Tc= 10
        end
    
    initial // one exec 
        begin
            $readmemh("testvector.tv",testvector); //read in hexa
            errors=0;
            vectornum=0;
            reset=1; #17;reset=0;
        end
    
    always @(posedge clk)
        begin
            Result_expected = testvector[vectornum][31:0];
            a = testvector[vectornum][63:32];
            b = testvector[vectornum][95:64];
            FPUControl = testvector[vectornum][97:96];
        end
    
    always @(negedge clk)
        begin
            if (~reset)
                begin 
                    if ((Result !== Result_expected))  // ===, == 
                        begin
                          $display("testvector: %h",testvector[vectornum]);
                          $display("Vectornum: %d",vectornum);
                          $display("Error input a: %h",{a});
                          $display("Error input b: %h",{b});
                          $display("Error input FPUControl: %h",{FPUControl});
                          $display("output Result:%h, Result_expected:%h",Result,Result_expected);
                          errors=errors+1; 
                        end
                    vectornum=vectornum+1;
                
                    if (testvector[vectornum][0] === 1'bx)
                        begin
                            $display("total errors: %d",errors);
                            $finish;
                        end  
                end
        end
    initial begin
      $dumpfile("fpu.vcd");
      $dumpvars;
    end
endmodule

FP Unit/fpu.vcd
$date
	Tue Jul 20 19:53:42 2021
$end
$version
	Icarus Verilog
$end
$timescale
	1ns
$end
$scope module fpu_tb $end
$var wire 32 ! Result [31:0] $end
$var reg 2 " FPUControl [1:0] $end
$var reg 32 # Result_expected [31:0] $end
$var reg 32 $ a [31:0] $end
$var reg 32 % b [31:0] $end
$var reg 1 & clk $end
$var reg 32 ' errors [31:0] $end
$var reg 1 ( reset $end
$var reg 32 ) vectornum [31:0] $end
$scope module dut $end
$var wire 2 * FPUControl [1:0] $end
$var wire 32 + a [31:0] $end
$var wire 32 , b [31:0] $end
$var reg 32 - Result [31:0] $end
$var reg 2 . control [1:0] $end
$var reg 32 / expoA [31:0] $end
$var reg 32 0 expoB [31:0] $end
$var reg 32 1 expoR [31:0] $end
$var reg 32 2 mantA [31:0] $end
$var reg 32 3 mantB [31:0] $end
$var reg 32 4 mantR [31:0] $end
$var reg 1 5 signA $end
$var reg 1 6 signB $end
$var reg 1 7 signR $end
$upscope $end
$upscope $end
$enddefinitions $end
#0
$dumpvars
07
x6
x5
bx 4
b0xxxxxxxxxxxxxxxxxxxxxxxx 3
b0xxxxxxxxxxxxxxxxxxxxxxxx 2
bx 1
b0xxxxxxxx 0
b0xxxxxxxx /
bx .
b0xxxxxxxxxxxxxxxxxxxxxxxxxxxxxxx -
bx ,
bx +
bx *
b0 )
1(
b0 '
1&
bx %
bx $
bx #
bx "
b0xxxxxxxxxxxxxxxxxxxxxxxxxxxxxxx !
$end
#5
0&
#10
b1000000000000000000000000000000 !
b1000000000000000000000000000000 -
b0 4
b10000000 1
b100000000000000000000000 3
b100000000000000000000000 2
b1111111 0
b1111111 /
06
05
b1 .
b1 "
b1 *
b111111100000000000000000000000 %
b111111100000000000000000000000 ,
b111111100000000000000000000000 $
b111111100000000000000000000000 +
b1000000000000000000000000000000 #
1&
#15
0&
#17
0(
#20
1&
#25
b1 )
0&
#30
b1000010000110100000000000000000 !
b1000010000110100000000000000000 -
b110100000000000000000 4
b10000100 1
b101110000000000000000000 3
b11111000000000000000000 2
b10000011 0
b10000010 /
b1000001101110000000000000000000 %
b1000001101110000000000000000000 ,
b1000001011110000000000000000000 $
b1000001011110000000000000000000 +
b1000010000110100000000000000000 #
1&
#35
b10 )
0&
#40
b1000001000000010000000000000000 !
b1000001000000010000000000000000 -
b10000000000000000 4
b10000010 1
b111111000000000000000000 3
b1100000000000000000 2
b10000001 0
b1111100 /
b1000000111111000000000000000000 %
b1000000111111000000000000000000 ,
b111110010000000000000000000000 $
b111110010000000000000000000000 +
b1000001000000010000000000000000 #
1&
#45
b11 )
0&
#50
b1000111110000110110000000100000 !
b1000111110000110110000000100000 -
b10000110110000000100000 4
b10001111 1
b10000 3
b110000110110000000010000 2
b1111100 0
b10001111 /
b111110000000000000000000000000 %
b111110000000000000000000000000 ,
b1000111110000110110000000010000 $
b1000111110000110110000000010000 +
b1000111110000110110000000100000 #
1&
#55
b100 )
0&
#60
b1000000010000000000000000000000 !
b1000000010000000000000000000000 -
b10000000000000000000000 4
b10000000 1
b110000000000000000000000 3
b110000000000000000000000 2
b1111111 0
b1111111 /
b111111110000000000000000000000 %
b111111110000000000000000000000 ,
b111111110000000000000000000000 $
b111111110000000000000000000000 +
b1000000010000000000000000000000 #
1&
#65
b101 )
0&
