FP Unit/fpu.v
module fpu(
    a,
    b,
    FPUControl,
    Result
);
    //32 bits: 1 bit sign, 8 bit expo, 23 bit mantisa
    //16 bits. 1 bit sign, 5 bit expo, 10 bit mantisa
    input [31:0] a, b;
    input [1:0] FPUControl;  //00 suma 16 bits, 01 suma 32 bits, 10 producto 16 bits, 11 producto 32 bits
    output reg [31:0] Result;

    reg signA;
    reg signB;
    reg [31:0] expoA;
    reg [31:0] expoB;
    reg [31:0] mantA;
    reg [31:0] mantB;
    
    reg sumaResta;
    reg signR;
    reg [31:0] expoR;
    reg [31:0] mantR;
    reg [31:0] mantAshift;
    reg [31:0] mantBshift;
    reg [47:0] productoPosible;
    reg [31:0] aux;
    reg [47:0] aux2;
    reg [1:0] control;

    always @(*) begin
        control = FPUControl;
        //Separo los componentes
        signA = FPUControl[0] ? a[31] : a[15];
        signB = FPUControl[0] ? b[31] : b[15];
        
        //Agrego 24 o 27 zeros delante del exponente
        expoA = FPUControl[0] ? {24'b0, a[30:23]} : {27'b0, a[14:10]};
        expoB = FPUControl[0] ? {24'b0, b[30:23]} : {27'b0, b[14:10]};

        //Agrego un 1 delante de la mantisa
        mantA = FPUControl[0] ? {9'b1, a[22:0]} : {22'b1, a[9:0]};
        mantB = FPUControl[0] ? {9'b1, b[22:0]} : {22'b1, b[9:0]};
        
        if (~FPUControl[1]) begin
            //Suma
            if ((a == 0 && b != 0) || a != 0 && b == 0) begin
                signR = (a == 0) ? signB : signA;
                expoR = (a == 0) ? expoB : expoA;
                mantR = (a == 0) ? mantB : mantA;
            end
            else if ((a == 0 && b == 0) || (signA != signB && expoA == expoB && mantA == mantB)) begin
                signR = 0;
                expoR = 0;
                mantR = 0;
            end
            else begin
                if (expoA > expoB) begin
                    expoR = expoA;
                    mantB = mantB >> (expoA - expoB);
                end
                else begin
                    expoR = expoB;
                    mantA = mantA >> (expoB - expoA);
                end

                //sumaResta, //0 sumar, 1 restar
                sumaResta = ~(signA == signB);

                if (sumaResta) begin
                    if (mantA > mantB) begin
                        mantR = mantA - mantB;
                        signR = signA;
                    end
                    else begin
                        mantR = mantB - mantA;
                        signR = signB;
                    end
                end
                else begin
                    mantR = mantA + mantB;
                    signR = signA;
                end
                    
                if (sumaResta) begin
                    //RESTA: Busco el primer 1
                    //mantR != 0, porque valido al inicio
                    aux = 0;
                    //En aux guardo en qué bit está el primer 1 a la izquierda
                    //naturalmente es menor a 23 o 10, ya que restamos el mayor - menor
                    aux2 = mantR;
                    while(~aux2[31]) begin
                        aux2 = aux2 << 1;
                        aux = aux + 1;
                    end
                    aux = 31 - aux;
                    //Este bit debe regresar a la posicion 23 o 10 para normalizar la mantisa
                    //Cada desplazamiento debe restar 1 al exponente
                    mantR = mantR << ((FPUControl[0] ? 23 : 10) - aux);
                    expoR = expoR - ((FPUControl[0] ? 23 : 10) - aux);
                end
                else begin
                    //SUMA:
                    if ((control[0] && mantR[24] == 1'b1) || (~control[0] && mantR[11] == 1'b1)) begin
                        //Overflow
                        mantR = mantR >> 1'b1;
                        expoR = expoR + 1'b1;
                    end
                end
                
                //Quitar el 1 delante de la mantisa
                mantR = FPUControl[0] ? mantR[22:0] : mantR[9:0];
            end
        end
        else begin
            if (a == 0 || b == 0) begin
                signR = 0;
                expoR = 0;
                mantR = 0;
            end
            else begin
                expoR = expoA + expoB - (FPUControl[0] ? 8'b01111111 : 5'b01111);
                //Desplazo a la derecha las mantisas eliminando todos los ending zeros.
                mantAshift = 0; //Guarda cuantos bits a la derecha se mueve.
                mantBshift = 0;
                while(~mantA[0]) begin
                    mantA = mantA >> 1;
                    mantAshift = mantAshift + 1;
                end
                while(~mantB[0]) begin
                    mantB = mantB >> 1;
                    mantBshift = mantBshift + 1;
                end
                
                //Multiplico las mantisas, máximo número puede ser de 48 bits o 22 bits
                if (FPUControl[0])
                    productoPosible = {16'b0, mantA} * {16'b0, mantB};
                else
                    productoPosible = mantA * mantB;
                
                aux = 0;
                //productoPosible tiene 1 o 2 bits de parte entera
                //En aux guardo en qué bit está el primer 1 a la izquierda
                aux2 = productoPosible;
                while(~aux2[47]) begin
                    aux2 = aux2 << 1;
                    aux = aux + 1;
                end
                aux = 47 - aux;
                //Si aux+1 - # bits decimales en ambas mantisas > 1 (=2), sumo uno al exponente
                if ( ( (aux + 1) - ((FPUControl[0] ? 23 : 10) - mantAshift + (FPUControl[0] ? 23 : 10) - mantBshift) ) > 1) begin
                    expoR = expoR + 1;
                end

                //Caso 1: aux = 23, entonces ya tiene forma de mantisa (leading 1 y 23 bits después, 0 a 22)
                //Caso 1: aux = 10, entonces ya tiene forma de mantisa (leading 1 y 10 bits después, 0 a 9)
                //Caso 2: aux > 23, shift right, se puede perder información en los bits menos significativos
                //Caso 2: aux > 10, shift right, se puede perder información en los bits menos significativos
                if (aux > (FPUControl[0] ? 23 : 10))
                    productoPosible = productoPosible >> (aux - (FPUControl[0] ? 23 : 10));
                //Caso 3: aux < 23, shift left para darle forma
                //Caso 3: aux < 10, shift left para darle forma
                if (aux < (FPUControl[0] ? 23 : 10))
                    productoPosible = productoPosible << ((FPUControl[0] ? 23 : 10) - aux);

                //Quitar el 1 delante de la mantisa
                mantR = FPUControl[0] ? productoPosible[22:0] : productoPosible[9:0];

                //Signo
                signR = signA ^ signB;
            end
        end
        Result = FPUControl[0] ? {signR, expoR[7:0], mantR[22:0]} : {signR, expoR[4:0], mantR[9:0]};
    end
    
endmodule

FP Unit/fpu_tb.v
`timescale 1ns/1ns

/*
//testvector.tv
//FPUControl_A_B_Resultexpected
//01
//1.0 + 1.0=2.0
//23.0 + 15.5 = 38.5
//7.875 + 0.1875 = 8.0625
//0.125 + 100032.125 = 100032.25
//1.5 + 1.5 = 3.0
//1.5 + 0 = 1.5
//0 + 1.5 = 1.5
//-1.5 + 1.5 = 0
//1.5 - 1.5 = 0
//6.875 - 15.5 = -8.625
//15.5 - 6.875 = 8.625
//00
//1.625 + 0.5 = 2.125 
//0.875 + 10.5 = 11.375
//64.4375+18.015625 = 82.453125
//11:
//1.0 * 1.0 = 1.0
//1.5 * 1.5 = 2.25
//312.4375 * 124.8125 = 38996.10546875
//0.03125 * 7.8125 = 0.244140625 
//-1*-1 = 1
//-1*1 = -1
//1*-1 = -1
//1*1=1
//0*0=0
//10:
//1.625 * 0.5 = 0.8125
//0.03125 * 7.8125 = 0.244140625 
//0*0=0
*/

module fpu_tb();
    reg [31:0] a,b;
    reg [1:0] FPUControl;
    wire [31:0] Result;

    reg clk, reset;
    reg [101:0] testvector[1000:0];
    
    reg [31:0] Result_expected; // to compare y output
    reg [31:0] vectornum; // check testvector number
    reg [31:0] errors; // error counter
    
    fpu dut(.a(a), .b(b), .FPUControl(FPUControl), .Result(Result));
    
    always// always execute
        begin
            clk=1; #5; clk=0; #5;   //period? Tc= 10
        end
    
    initial // one exec 
        begin
            $readmemh("testvector.tv",testvector); //read in hexa
            errors=0;
            vectornum=0;
            reset=1; #17;reset=0;
        end
    
    always @(posedge clk)
        begin
            Result_expected = testvector[vectornum][31:0];
            a = testvector[vectornum][63:32];
            b = testvector[vectornum][95:64];
            FPUControl = testvector[vectornum][97:96];
        end
    
    always @(negedge clk)
        begin
            if (~reset)
                begin 
                    if ((Result !== Result_expected))  // ===, == 
                        begin
                          $display("testvector: %h",testvector[vectornum]);
                          $display("Vectornum: %d",vectornum);
                          $display("Error input a: %h",{a});
                          $display("Error input b: %h",{b});
                          $display("Error input FPUControl: %h",{FPUControl});
                          $display("output Result:%h, Result_expected:%h",Result,Result_expected);
                          errors=errors+1; 
                        end
                    vectornum=vectornum+1;
                
                    if (testvector[vectornum][0] === 1'bx)
                        begin
                            $display("total errors: %d",errors);
                            $finish;
                        end  
                end
        end
    initial begin
      $dumpfile("fpu.vcd");
      $dumpvars;
    end
endmodule

FP Unit/fpu.vcd
$date
	Wed Jul 21 10:04:08 2021
$end
$version
	Icarus Verilog
$end
$timescale
	1ns
$end
$scope module fpu_tb $end
$var wire 32 ! Result [31:0] $end
$var reg 2 " FPUControl [1:0] $end
$var reg 32 # Result_expected [31:0] $end
$var reg 32 $ a [31:0] $end
$var reg 32 % b [31:0] $end
$var reg 1 & clk $end
$var reg 32 ' errors [31:0] $end
$var reg 1 ( reset $end
$var reg 32 ) vectornum [31:0] $end
$scope module dut $end
$var wire 2 * FPUControl [1:0] $end
$var wire 32 + a [31:0] $end
$var wire 32 , b [31:0] $end
$var reg 32 - Result [31:0] $end
$var reg 32 . aux [31:0] $end
$var reg 48 / aux2 [47:0] $end
$var reg 2 0 control [1:0] $end
$var reg 32 1 expoA [31:0] $end
$var reg 32 2 expoB [31:0] $end
$var reg 32 3 expoR [31:0] $end
$var reg 32 4 mantA [31:0] $end
$var reg 32 5 mantAshift [31:0] $end
$var reg 32 6 mantB [31:0] $end
$var reg 32 7 mantBshift [31:0] $end
$var reg 32 8 mantR [31:0] $end
$var reg 48 9 productoPosible [47:0] $end
$var reg 1 : signA $end
$var reg 1 ; signB $end
$var reg 1 < signR $end
$var reg 1 = sumaResta $end
$upscope $end
$upscope $end
$enddefinitions $end
#0
$dumpvars
x=
x<
x;
x:
bx 9
bx 8
bx 7
bx 6
bx 5
bx 4
bx 3
bx 2
bx 1
bx 0
bx /
bx .
bx -
bx ,
bx +
bx *
b0 )
1(
b0 '
1&
bx %
bx $
bx #
bx "
bx !
$end
#5
0&
#10
b1000000000000000000000000000000 !
b1000000000000000000000000000000 -
0<
b0 8
0=
b10000000 3
b100000000000000000000000 6
b100000000000000000000000 4
b1111111 2
b1111111 1
0;
0:
b1 0
b1 "
b1 *
b111111100000000000000000000000 %
b111111100000000000000000000000 ,
b111111100000000000000000000000 $
b111111100000000000000000000000 +
b1000000000000000000000000000000 #
1&
#15
0&
#17
0(
#20
1&
#25
b1 )
0&
#30
b1000010000110100000000000000000 !
b1000010000110100000000000000000 -
b110100000000000000000 8
b10000100 3
b101110000000000000000000 6
b11111000000000000000000 4
b10000011 2
b10000010 1
b1000001101110000000000000000000 %
b1000001101110000000000000000000 ,
b1000001011110000000000000000000 $
b1000001011110000000000000000000 +
b1000010000110100000000000000000 #
1&
#35
b10 )
0&
#40
b1000001000000010000000000000000 !
b1000001000000010000000000000000 -
b10000000000000000 8
b10000010 3
b111111000000000000000000 6
b1100000000000000000 4
b10000001 2
b1111100 1
b1000000111111000000000000000000 %
b1000000111111000000000000000000 ,
b111110010000000000000000000000 $
b111110010000000000000000000000 +
b1000001000000010000000000000000 #
1&
#45
b11 )
0&
#50
b1000111110000110110000000100000 !
b1000111110000110110000000100000 -
b10000110110000000100000 8
b10001111 3
b10000 6
b110000110110000000010000 4
b1111100 2
b10001111 1
b111110000000000000000000000000 %
b111110000000000000000000000000 ,
b1000111110000110110000000010000 $
b1000111110000110110000000010000 +
b1000111110000110110000000100000 #
1&
#55
b100 )
0&
#60
b1000000010000000000000000000000 !
b1000000010000000000000000000000 -
b10000000000000000000000 8
b10000000 3
b110000000000000000000000 6
b110000000000000000000000 4
b1111111 2
b1111111 1
b111111110000000000000000000000 %
b111111110000000000000000000000 ,
b111111110000000000000000000000 $
b111111110000000000000000000000 +
b1000000010000000000000000000000 #
1&
#65
b101 )
0&
#70
b111111110000000000000000000000 !
b111111110000000000000000000000 -
b110000000000000000000000 8
b1111111 3
b100000000000000000000000 4
b0 1
b0 $
b0 +
b111111110000000000000000000000 #
1&
#75
b110 )
0&
#80
b100000000000000000000000 6
b110000000000000000000000 4
b0 2
b1111111 1
b0 %
b0 ,
b111111110000000000000000000000 $
b111111110000000000000000000000 +
1&
#85
b111 )
0&
#90
b0 !
b0 -
b0 8
b0 3
b110000000000000000000000 6
b1111111 2
1;
b10111111110000000000000000000000 %
b10111111110000000000000000000000 ,
b0 #
1&
#95
b1000 )
0&
#100
0;
1:
b111111110000000000000000000000 %
b111111110000000000000000000000 ,
b10111111110000000000000000000000 $
b10111111110000000000000000000000 +
1&
#105
b1001 )
0&
#110
b11000001000010100000000000000000 !
b11000001000010100000000000000000 -
b10001010000000000000000000000000 /
b10111 .
1<
b10100000000000000000 8
1=
b10000010 3
b11011100000000000000000 6
b111110000000000000000000 4
b10000001 2
b10000010 1
b1000000110111000000000000000000 %
b1000000110111000000000000000000 ,
b11000001011110000000000000000000 $
b11000001011110000000000000000000 +
b11000001000010100000000000000000 #
1&
#115
b1010 )
0&
#120
b1000001000010100000000000000000 !
b1000001000010100000000000000000 -
b10001010000000000000000000000000 /
b10111 .
0<
b10100000000000000000 8
b111110000000000000000000 6
b11011100000000000000000 4
b10000010 2
b10000001 1
b1000001011110000000000000000000 %
b1000001011110000000000000000000 ,
b11000000110111000000000000000000 $
b11000000110111000000000000000000 +
b1000001000010100000000000000000 #
1&
#125
b1011 )
0&
#130
b100000001000000 !
b100000001000000 -
b1000000 8
0=
b10000 3
b11010000000 6
b1000000000 4
b1111 2
b1110 1
0:
b0 0
b0 "
b0 *
b11111010000000 %
b11111010000000 ,
b11100000000000 $
b11100000000000 +
b100000001000000 #
1&
#135
b1100 )
0&
#140
b100100110110000 !
b100100110110000 -
b110110000 8
b10010 3
b1110000 6
b10101000000 4
b1110 2
b10010 1
b11101100000000 %
b11101100000000 ,
b100100101000000 $
b100100101000000 +
b100100110110000 #
1&
#145
b1101 )
0&
#150
b101010100100111 !
b101010100100111 -
b100100111 8
b10101 3
b10000000111 6
b100100000 4
b10101 2
b10011 1
b101010000000111 %
b101010000000111 ,
b100110010000001 $
b100110010000001 +
b101010100100111 #
1&
#155
b1110 )
0&
#160
b111111100000000000000000000000 !
b111111100000000000000000000000 -
b0 8
b100000000000000000000000000000000000000000000000 /
b0 .
b100000000000000000000000 9
b10111 7
b10111 5
b1111111 3
b1 6
b1 4
b1111111 2
b1111111 1
b11 0
b11 "
b11 *
b111111100000000000000000000000 %
b111111100000000000000000000000 ,
b111111100000000000000000000000 $
b111111100000000000000000000000 +
b111111100000000000000000000000 #
1&
#165
b1111 )
0&
#170
b1000000000100000000000000000000 !
b1000000000100000000000000000000 -
b100000000000000000000 8
b10000000 3
b11 .
b100100000000000000000000000000000000000000000000 /
b100100000000000000000000 9
b10110 7
b10110 5
b11 6
b11 4
b111111110000000000000000000000 %
b111111110000000000000000000000 ,
b111111110000000000000000000000 $
b111111110000000000000000000000 +
b1000000000100000000000000000000 #
1&
#175
b10000 )
0&
#180
b1000111000110000101010000011011 !
b1000111000110000101010000011011 -
b110000101010000011011 8
b100110000101010000011011000000000000000000000000 /
b10111 .
b100110000101010000011011 9
b1011 7
b1101 5
b10001110 3
b1001110000111 6
b11111001101 4
b10000111 2
b10000101 1
b1000011100111000011100000000000 %
b1000011100111000011100000000000 ,
b1000010111110011010000000000000 $
b1000010111110011010000000000000 +
b1000111000110000101010000011011 #
1&
#185
b10001 )
0&
#190
b111110011110100000000000000000 !
b111110011110100000000000000000 -
b11110100000000000000000 8
b111110100000000000000000000000000000000000000000 /
b110 .
b111110100000000000000000 9
b10111 7
b10001 5
b1111100 3
b1 6
b1111101 4
b1111010 2
b10000001 1
b111101000000000000000000000000 %
b111101000000000000000000000000 ,
b1000000111110100000000000000000 $
b1000000111110100000000000000000 +
b111110011110100000000000000000 #
1&
#195
b10010 )
0&
#200
b111111100000000000000000000000 !
b111111100000000000000000000000 -
b0 8
b100000000000000000000000000000000000000000000000 /
b0 .
b100000000000000000000000 9
b10111 7
b10111 5
b1111111 3
b1 6
b1 4
b1111111 2
b1111111 1
1;
1:
b10111111100000000000000000000000 %
b10111111100000000000000000000000 ,
b10111111100000000000000000000000 $
b10111111100000000000000000000000 +
b111111100000000000000000000000 #
1&
#205
b10011 )
0&
#210
b10111111100000000000000000000000 !
b10111111100000000000000000000000 -
1<
b0 .
b100000000000000000000000000000000000000000000000 /
b100000000000000000000000 9
b10111 7
b10111 5
b1 6
b1 4
0:
b111111100000000000000000000000 $
b111111100000000000000000000000 +
b10111111100000000000000000000000 #
1&
#215
b10100 )
0&
#220
b0 .
b100000000000000000000000000000000000000000000000 /
b100000000000000000000000 9
b10111 7
b10111 5
b1 6
b1 4
0;
1:
b111111100000000000000000000000 %
b111111100000000000000000000000 ,
b10111111100000000000000000000000 $
b10111111100000000000000000000000 +
1&
#225
b10101 )
0&
#230
b111111100000000000000000000000 !
b111111100000000000000000000000 -
0<
b0 .
b100000000000000000000000000000000000000000000000 /
b100000000000000000000000 9
b10111 7
b10111 5
b1 6
b1 4
0:
b111111100000000000000000000000 $
b111111100000000000000000000000 +
b111111100000000000000000000000 #
1&
#235
b10110 )
0&
#240
b0 !
b0 -
b0 3
b100000000000000000000000 6
b100000000000000000000000 4
b0 2
b0 1
b0 %
b0 ,
b0 $
b0 +
b0 #
1&
#245
b10111 )
0&
#250
b11101010000000 !
b11101010000000 -
b1010000000 8
b11 .
b110100000000000000000000000000000000000000000000 /
b11010000000 9
b111 7
b1010 5
b1110 3
b1101 6
b1 4
b1111 2
b1110 1
b10 0
b10 "
b10 *
b11111010000000 %
b11111010000000 ,
b11100000000000 $
b11100000000000 +
b11101010000000 #
1&
#255
b11000 )
0&
#260
b11001111010000 !
b11001111010000 -
b1111010000 8
b111110100000000000000000000000000000000000000000 /
b110 .
b11111010000 9
b1010 7
b100 5
b1100 3
b1 6
b1111101 4
b1010 2
b10001 1
b10100000000000 %
b10100000000000 ,
b100011111010000 $
b100011111010000 +
b11001111010000 #
1&
#265
b11001 )
0&
#270
b0 !
b0 -
b0 8
b0 3
b10000000000 6
b10000000000 4
b0 2
b0 1
b0 %
b0 ,
b0 $
b0 +
b0 #
1&
#275
b11010 )
0&
