ALU/alu.v
//AGREGAR MUL, UMULL, SMULL
module alu(
    a,
    b,
    ALUControl,
    Result1,
    Result2,
    ALUFlags
);

  input [31:0] a, b;
  input [2:0] ALUControl;
  output reg [31:0] Result1;
  output reg [31:0] Result2;
  output wire [3:0] ALUFlags;
  
  wire signed [31:0] signed_a = a;
  wire signed [31:0] signed_b = b;
  wire [32:0] sum;
  wire neg, zero, carry, overflow;
  
  assign sum = a + (ALUControl[0]? ~b:b) + ALUControl[0];

  always @(*)
    begin
      casex (ALUControl[2:0]) 
        3'b00?: Result1=sum;
        3'b010: Result1=a&b;
				3'b011: Result1=a|b;
        3'b100: Result1 = a*b;
        3'b101: {Result1, Result2} = a*b;
        3'b110: {Result1, Result2} = signed_a*signed_b;
    	endcase    
    end
  
  assign neg = Result[31];
  assign zero = (Result == 32'b0); 
  assign carry = (ALUControl[1]==1'b0) & sum[32];
  assign overflow = (ALUControl[1]==1'b0) & (sum[31] 
	^ a[31])  & ~(ALUControl[0] ^ a[31] ^ b[31]);
  
  assign ALUFlags= {neg, zero, carry, overflow};
  
endmodule

ALU/alu_tb.v
//MODIFICAR (en testvector tbn):
`timescale 1ns/1ns

module alu_tb();
    reg clk, reset;
    reg [31:0] a,b;
    reg [31:0] Result_1_expected; // to compare y output
    reg [31:0] Result_2_expected; // to compare y output
    reg [3:0] ALUFlags_expected;  // to compare y output
    reg [2:0] ALUControl;

    wire [31:0] Result1;
    wire [31:0] Result2;
    wire [3:0] ALUFlags;
    
    reg [31:0] vectornum; // check testvector number
    reg [31:0] errors; // error counter
    
    reg [134:0] testvector[1000:0];

    alu dut(.a(a), .b(b), .ALUControl(ALUControl), .Result1(Result1), .Result2(Result2), .ALUFlags(ALUFlags));
    
    always// always execute
        begin
            clk=1; #5; clk=0; #5;   //period? Tc= 10
        end
    
    initial // one exec 
        begin
            $readmemh("testvector.tv",testvector); //read in hexa
            errors=0;
            vectornum=0;
            reset=1; #17;reset=0;
        end
    
    always @(posedge clk)
        begin
           {ALUControl, a, b, Result_1_expected, Result_2_expected, ALUFlags_expected} = testvector[vectornum];
        end
    
    always @(negedge clk)
        begin
            if (~reset)
                begin 
                    if ((Result1 !== Result_1_expected || Result2 !== Result_2_expected))  // ===, == 
                        begin
                          $display("testvector: %h",testvector[vectornum]);
                          $display("Vectornum: %d",vectornum);
                          $display("Error input a: %h",{a});
                          $display("Error input b: %h",{b});
                          $display("Error input ALUControl: %h",{ALUControl});
                          $display("output Result_1:%h, Result_1_expected:%h",Result1,Result_1_expected);
                          $display("output Result_2:%h, Result_2_expected:%h",Result2,Result_2_expected);
                          errors=errors+1; 
                        end
                    vectornum=vectornum+1;
                
                    if (testvector[vectornum][0] === 1'bx)
                        begin
                            $display("total errors: %d",errors);
                            $finish;
                        end  
                end
        end
    initial begin
      $dumpfile("alu.vcd");
      $dumpvars;
    end
endmodule

ALU/alu.vcd
$date
	Tue Jul 27 19:37:31 2021
$end
$version
	Icarus Verilog
$end
$timescale
	1ns
$end
$scope module alu_tb $end
$var wire 32 ! Result2 [31:0] $end
$var wire 32 " Result1 [31:0] $end
$var wire 4 # ALUFlags [3:0] $end
$var reg 3 $ ALUControl [2:0] $end
$var reg 4 % ALUFlags_expected [3:0] $end
$var reg 32 & Result_1_expected [31:0] $end
$var reg 32 ' Result_2_expected [31:0] $end
$var reg 32 ( a [31:0] $end
$var reg 32 ) b [31:0] $end
$var reg 1 * clk $end
$var reg 32 + errors [31:0] $end
$var reg 1 , reset $end
$var reg 32 - vectornum [31:0] $end
$scope module dut $end
$var wire 3 . ALUControl [2:0] $end
$var wire 32 / a [31:0] $end
$var wire 32 0 b [31:0] $end
$var wire 1 1 carry $end
$var wire 1 2 overflow $end
$var wire 32 3 signed_a [31:0] $end
$var wire 32 4 signed_b [31:0] $end
$var wire 1 5 zero $end
$var wire 33 6 sum [32:0] $end
$var wire 1 7 neg $end
$var wire 4 8 ALUFlags [3:0] $end
$var reg 32 9 Result1 [31:0] $end
$var reg 32 : Result2 [31:0] $end
$upscope $end
$upscope $end
$enddefinitions $end
#0
$dumpvars
bx :
bx 9
bx 8
x7
bx 6
x5
bx 4
bx 3
x2
x1
bx 0
bx /
bx .
b0 -
1,
b0 +
1*
bx )
bx (
bx '
bx &
bx %
bx $
bx #
bx "
bx !
$end
#5
0*
#10
02
01
07
b1 6
b100 #
b100 8
15
b0 "
b0 9
b100 $
b100 .
b1 3
b1 (
b1 /
b0 4
b0 )
b0 0
b0 &
b100 %
1*
#15
0*
#17
0,
#20
1*
#25
b1 -
0*
#30
b101 #
b101 8
12
b1 !
b1 :
b101 $
b101 .
b10000000000000000000000000000000 3
b1111111111111111111111111111110 6
b10000000000000000000000000000000 (
b10000000000000000000000000000000 /
b10 4
b10 )
b10 0
b1 '
b101 %
1*
#35
b10 -
0*
#40
02
17
b0 !
b0 :
b1000 #
b1000 8
05
b10000000000000000000000000000000 "
b10000000000000000000000000000000 9
b110 $
b110 .
b1000000000000000000000000000000 3
b1000000000000000000000000000010 6
b1000000000000000000000000000000 (
b1000000000000000000000000000000 /
b10000000000000000000000000000000 &
b0 '
b1000 %
1*
#45
b11 -
0*
